bitcart/__init__.py
bitcart/coin.py
bitcart/errors.py
bitcart/event_delivery.py
bitcart/logger.py
bitcart/manager.py
bitcart/py.typed
bitcart/types.py
bitcart/utils.py
bitcart/version.py
bitcart/coins/__init__.py
bitcart/coins/bch.py
bitcart/coins/bnb.py
bitcart/coins/btc.py
bitcart/coins/eth.py
bitcart/coins/grs.py
bitcart/coins/ltc.py
bitcart/coins/matic.py
bitcart/coins/trx.py
bitcart/coins/xmr.py
bitcart/coins/xrg.py
bitcart/providers/__init__.py
bitcart/providers/jsonrpcrequests.py
bitcart-1.19.0.0.dist-info/METADATA
bitcart-1.19.0.0.dist-info/WHEEL
bitcart-1.19.0.0.dist-info/licenses/LICENSE
bitcart-1.19.0.0.dist-info/RECORD
