Metadata-Version: 2.4
Name: bitcart
Version: 1.19.0.0
Summary: Bitcart coins support library
Project-URL: Homepage, https://github.com/bitcart/bitcart-sdk
Project-URL: Source, https://github.com/bitcart/bitcart-sdk
Project-URL: Changelog, https://github.com/bitcart/bitcart-sdk/blob/master/CHANGELOG.md
Author-email: MrNaif2018 <chuff184@gmail.com>
License-Expression: MIT
License-File: LICENSE
Keywords: bitcart,bitcartcc,daemon,electrum
Classifier: Development Status :: 5 - Production/Stable
Classifier: Intended Audience :: Developers
Classifier: License :: OSI Approved :: MIT License
Classifier: Programming Language :: Python :: 3
Classifier: Programming Language :: Python :: 3.12
Classifier: Programming Language :: Python :: 3.13
Classifier: Programming Language :: Python :: 3.14
Classifier: Topic :: Software Development :: Build Tools
Requires-Python: >=3.12
Requires-Dist: aiohttp
Requires-Dist: jsonrpcclient
Requires-Dist: universalasync
Provides-Extra: proxy
Requires-Dist: aiohttp-socks; extra == 'proxy'
